alttester/__init__.py
alttester/__version__.py
alttester/_websocket.py
alttester/altdriver.py
alttester/altobject.py
alttester/by.py
alttester/exceptions.py
alttester/keycode.py
alttester/logging.py
alttester/playerpref.py
alttester/reverse_port_forwarding.py
alttester/commands/__init__.py
alttester/commands/base_command.py
alttester/commands/get_png_screenshot.py
alttester/commands/get_server_version.py
alttester/commands/get_static_property.py
alttester/commands/set_static_property.py
alttester/commands/AltTesterCommands/__init__.py
alttester/commands/AltTesterCommands/add_notification_listener.py
alttester/commands/AltTesterCommands/remove_notification_listener.py
alttester/commands/AltTesterCommands/reset_input.py
alttester/commands/AltTesterCommands/set_server_logging.py
alttester/commands/FindObjects/__init__.py
alttester/commands/FindObjects/find_object.py
alttester/commands/FindObjects/find_object_at_coordinates.py
alttester/commands/FindObjects/find_object_which_contains.py
alttester/commands/FindObjects/find_objects.py
alttester/commands/FindObjects/find_objects_which_contains.py
alttester/commands/FindObjects/wait_for_component_property.py
alttester/commands/FindObjects/wait_for_object.py
alttester/commands/FindObjects/wait_for_object_to_not_be_present.py
alttester/commands/FindObjects/wait_for_object_which_contains.py
alttester/commands/FindObjects/wait_for_visual_element_property.py
alttester/commands/InputActions/__init__.py
alttester/commands/InputActions/begin_touch.py
alttester/commands/InputActions/click_coordinates.py
alttester/commands/InputActions/end_touch.py
alttester/commands/InputActions/keys_down.py
alttester/commands/InputActions/keys_up.py
alttester/commands/InputActions/move_mouse.py
alttester/commands/InputActions/move_touch.py
alttester/commands/InputActions/multi_point_swipe.py
alttester/commands/InputActions/press_keys.py
alttester/commands/InputActions/scroll_mouse.py
alttester/commands/InputActions/swipe.py
alttester_driver-2.2.7.dist-info/METADATA
alttester_driver-2.2.7.dist-info/WHEEL
alttester_driver-2.2.7.dist-info/top_level.txt
alttester_driver-2.2.7.dist-info/RECORD
