Metadata-Version: 2.4
Name: AltTester-Driver
Version: 2.2.7
Summary: Python bindings for the AltTester® framework. AltTester® is an open-source UI driven test automation tool that helps you find objects in your game and interacts with them.
Home-page: https://alttester.com/docs/sdk/latest/
Author: Altom Consulting
Author-email: contact@alttester.com
License: GNU GPLv3
Project-URL: Bug Tracker, https://github.com/alttester/AltTester-Unity-SDK/issues
Project-URL: Documentation, https://alttester.com/docs/sdk/latest
Project-URL: Source, https://github.com/alttester/AltTester-Unity-SDK
Keywords: unity testing tests
Classifier: Development Status :: 5 - Production/Stable
Classifier: Intended Audience :: Developers
Classifier: Intended Audience :: Other Audience
Classifier: License :: OSI Approved :: GNU General Public License v3 (GPLv3)
Classifier: Programming Language :: C#
Classifier: Programming Language :: Java
Classifier: Programming Language :: Cython
Classifier: Programming Language :: Python :: Implementation
Classifier: Programming Language :: Python :: Implementation :: CPython
Classifier: Programming Language :: Python :: 3 :: Only
Classifier: Programming Language :: Python :: 3.4
Classifier: Programming Language :: Python :: 3.5
Classifier: Programming Language :: Python :: 3.6
Classifier: Programming Language :: Python :: 3.7
Classifier: Programming Language :: Python :: 3.8
Classifier: Programming Language :: Python :: 3.9
Classifier: Operating System :: OS Independent
Classifier: Topic :: Games/Entertainment
Classifier: Topic :: Software Development :: Libraries
Classifier: Topic :: Software Development :: Testing
Classifier: Topic :: Software Development :: Testing :: Acceptance
Classifier: Topic :: Software Development :: Testing :: Unit
Requires-Python: >=3.4.0
Requires-Dist: loguru
Requires-Dist: deprecated
Requires-Dist: websocket-client
Requires-Dist: pure-python-adb
Dynamic: author
Dynamic: author-email
Dynamic: classifier
Dynamic: description
Dynamic: description-content-type
Dynamic: home-page
Dynamic: keywords
Dynamic: license
Dynamic: project-url
Dynamic: requires-dist
Dynamic: requires-python
Dynamic: summary
